setup.py
m79atomic.egg-info/PKG-INFO
m79atomic.egg-info/SOURCES.txt
m79atomic.egg-info/dependency_links.txt
m79atomic.egg-info/top_level.txt
xenon/__init__.py
xenon/arg_trans.py
xenon/xenon.py