Metadata-Version: 1.1
Name: m79atomic
Version: 2.0.1
Summary: minus79's atomic libs
Home-page: UNKNOWN
Author: Minus Seventynine
Author-email: gergely06@gmail.com
License: UNKNOWN
Platform: UNKNOWN
Classifier: Programming Language :: Python
Classifier: Programming Language :: Python :: 2
Classifier: License :: OSI Approved :: GNU General Public License (GPL)
Classifier: Operating System :: OS Independent
Classifier: Development Status :: 1 - Planning
Classifier: Environment :: Console
Classifier: Intended Audience :: End Users/Desktop
Classifier: Topic :: Desktop Environment
